{
  "subjectId": "maogai",
  "chapterId": "ch12",
  "generatedAt": "2026-06-21",
  "examConfig": {
    "source": "docs/refer/考试题型分布.md",
    "totalPoints": 100,
    "timeLimit": 50
  },
  "questions": [
    {
      "id": "q001",
      "type": "single_choice",
      "difficulty": "basic",
      "source": "current_chapter",
      "sourceChapter": "ch12",
      "points": 2,
      "sourceRef": {
        "path": "content/maogai/detail/12.1.md",
        "label": "毛泽东思想的活的灵魂"
      },
      "stem": "毛泽东思想的活的灵魂三个基本方面，排在第一位的是（　）。",
      "options": [
        "实事求是",
        "群众路线",
        "独立自主",
        "统一战线"
      ],
      "answer": 0,
      "hint": "实事求是是精髓和基本点。",
      "explanation": "A正确。12.1.md：活的灵魂三方面中实事求是排第一，是毛泽东思想的精髓。B、C是另两方面；D是三大法宝。"
    },
    {
      "id": "q002",
      "type": "single_choice",
      "difficulty": "basic",
      "source": "current_chapter",
      "sourceChapter": "ch12",
      "points": 2,
      "sourceRef": {
        "path": "content/maogai/detail/12.1.md",
        "label": "实事求是的内涵"
      },
      "stem": "实事求是的内涵是（　）。",
      "options": [
        "一切从实际出发，理论联系实际，在实践中检验真理和发展真理",
        "一切从书本出发，照搬外国经验",
        "一切从主观愿望出发，忽视实践",
        "只讲实践不讲理论"
      ],
      "answer": 0,
      "hint": "实事、是、求三字含义。",
      "explanation": "A正确。12.1.md完整内涵表述。B、C、D均违背实事求是。"
    },
    {
      "id": "q003",
      "type": "single_choice",
      "difficulty": "basic",
      "source": "current_chapter",
      "sourceChapter": "ch12",
      "points": 2,
      "sourceRef": {
        "path": "content/maogai/detail/12.1.md",
        "label": "1930年：《反对本本主义》"
      },
      "stem": "1930年毛泽东在《反对本本主义》中提出的著名论断是（　）。",
      "options": [
        "没有调查就没有发言权",
        "枪杆子里面出政权",
        "星星之火，可以燎原",
        "知己知彼，百战不殆"
      ],
      "answer": 0,
      "hint": "实事求是思想的早期表达。",
      "explanation": "A正确。12.1.md：1930年《反对本本主义》提出“没有调查就没有发言权”。B是八七会议；C是1930年另一文章；D是古代军事思想。"
    },
    {
      "id": "q004",
      "type": "single_choice",
      "difficulty": "basic",
      "source": "current_chapter",
      "sourceChapter": "ch12",
      "points": 2,
      "sourceRef": {
        "path": "content/maogai/detail/12.2.md",
        "label": "群众路线的内涵"
      },
      "stem": "群众路线的完整表述是（　）。",
      "options": [
        "一切为了群众，一切依靠群众，从群众中来，到群众中去，把党的正确主张变为群众的自觉行动",
        "一切为了领导，一切依靠上级指示",
        "从书本中来，到书本中去",
        "一切为了少数精英，一切依靠外援"
      ],
      "answer": 0,
      "hint": "价值立场+工作方法。",
      "explanation": "A正确。12.2.md完整内涵。B、C、D均歪曲群众路线。"
    },
    {
      "id": "q005",
      "type": "single_choice",
      "difficulty": "basic",
      "source": "current_chapter",
      "sourceChapter": "ch12",
      "points": 2,
      "sourceRef": {
        "path": "content/maogai/detail/12.3.md",
        "label": "独立自主的内涵"
      },
      "stem": "关于独立自主，下列理解正确的是（　）。",
      "options": [
        "既依靠自身力量，也积极争取外援，学习外国有益事物",
        "完全闭关锁国，拒绝一切对外交流",
        "完全依赖外国安排发展道路",
        "只讲外援不讲自身力量"
      ],
      "answer": 0,
      "hint": "独立自主不等于闭关自守。",
      "explanation": "A正确。12.3.md：独立自主既依靠自身力量，也积极争取外援和学习外国有益事物。B、C、D均片面。"
    },
    {
      "id": "q006",
      "type": "single_choice",
      "difficulty": "basic",
      "source": "current_chapter",
      "sourceChapter": "ch12",
      "points": 2,
      "sourceRef": {
        "path": "content/maogai/detail/12.1.md",
        "label": "1945年：党的七大"
      },
      "stem": "实事求是正式确立为党的思想路线是在（　）。",
      "options": [
        "1945年党的七大",
        "1921年党的一大",
        "1978年十一届三中全会",
        "2012年党的十八大"
      ],
      "answer": 0,
      "hint": "确立过程时间线最后一环。",
      "explanation": "A正确。12.1.md：1945年七大正式确立。B是建党；C是重新确立；D时间不符。"
    },
    {
      "id": "q007",
      "type": "single_choice",
      "difficulty": "basic",
      "source": "current_chapter",
      "sourceChapter": "ch12",
      "points": 2,
      "sourceRef": {
        "path": "content/maogai/detail/12.3.md",
        "label": "要讲政治条件，连半个手指头都不行"
      },
      "stem": "1958年毛泽东在长波电台和共同舰队问题上的表态，体现的是（　）。",
      "options": [
        "涉及国家主权绝不让步的独立自主原则",
        "对外依赖苏联决策",
        "放弃国防建设",
        "与苏联无条件结盟"
      ],
      "answer": 0,
      "hint": "所有权必须是中国的。",
      "explanation": "A正确。12.3.md：毛泽东指出要讲政治条件连半个手指头都不行，所有权必须是中国。B、C、D与史实相反。"
    },
    {
      "id": "q008",
      "type": "single_choice",
      "difficulty": "basic",
      "source": "current_chapter",
      "sourceChapter": "ch12",
      "points": 2,
      "sourceRef": {
        "path": "content/maogai/detail/12.2.md",
        "label": "坚持群众路线的三个层面"
      },
      "stem": "坚持群众路线，其核心要求是（　）。",
      "options": [
        "全心全意为人民服务",
        "追求利润最大化",
        "脱离群众精英治国",
        "只讲方法不讲立场"
      ],
      "answer": 0,
      "hint": "根本宗旨。",
      "explanation": "A正确。12.2.md：核心是全心全意为人民服务。B是资本主义逻辑；C、D与群众路线相悖。"
    },
    {
      "id": "q009",
      "type": "single_choice",
      "difficulty": "basic",
      "source": "review",
      "sourceChapter": "ch03",
      "points": 2,
      "sourceRef": {
        "path": "content/maogai/detail/3.2.md",
        "label": "毛泽东思想的主要内容"
      },
      "stem": "下列不属于毛泽东思想活的灵魂的是（　）。",
      "options": [
        "实事求是",
        "武装斗争",
        "群众路线",
        "独立自主"
      ],
      "answer": 1,
      "hint": "武装斗争是三大法宝之一。",
      "explanation": "B正确（选不属于）。3.2.md：活的灵魂是实事求是、群众路线、独立自主。武装斗争是三大法宝。"
    },
    {
      "id": "q010",
      "type": "single_choice",
      "difficulty": "basic",
      "source": "review",
      "sourceChapter": "ch07",
      "points": 2,
      "sourceRef": {
        "path": "content/maogai/detail/7.1.md",
        "label": "抗日民族统一战线"
      },
      "stem": "抗日民族统一战线中，中国共产党坚持的重要原则是（　）。",
      "options": [
        "独立自主",
        "一切服从国民党",
        "放弃武装斗争",
        "解散共产党"
      ],
      "answer": 0,
      "hint": "既维护团结抗战，又保持独立性。",
      "explanation": "A正确。7.1.md：抗日统一战线中坚持独立自主，保持思想上政治上组织上独立性。B、C、D均错误。"
    },
    {
      "id": "q011",
      "type": "single_choice",
      "difficulty": "basic",
      "source": "review",
      "sourceChapter": "ch08",
      "points": 2,
      "sourceRef": {
        "path": "content/maogai/detail/8.2.md",
        "label": "1953年2月：毛泽东南下调研"
      },
      "stem": "1953年2月毛泽东南下调研，体现了哪一思想方法的传统？（　）",
      "options": [
        "注重调查研究、实事求是",
        "闭门造车、主观臆断",
        "照搬外国模式",
        "脱离群众决策"
      ],
      "answer": 0,
      "hint": "调研后更加坚定改造决心。",
      "explanation": "A正确。8.2.md：毛泽东遵循注重调研传统南下调研。B、C、D与事实相反。"
    },
    {
      "id": "q012",
      "type": "single_choice",
      "difficulty": "basic",
      "source": "review",
      "sourceChapter": "ch05",
      "points": 2,
      "sourceRef": {
        "path": "content/maogai/detail/5.2.md",
        "label": "新民主主义革命总路线"
      },
      "stem": "新民主主义革命总路线中，革命的领导力量是（　）。",
      "options": [
        "无产阶级及其政党中国共产党",
        "民族资产阶级",
        "农民阶级单独领导",
        "小资产阶级"
      ],
      "answer": 0,
      "hint": "“新”的根本体现。",
      "explanation": "A正确。5.2.md：领导力量是无产阶级及其政党。B、C、D均非领导力量。"
    },
    {
      "id": "q013",
      "type": "single_choice",
      "difficulty": "basic",
      "source": "review",
      "sourceChapter": "ch12",
      "points": 2,
      "sourceRef": {
        "path": "content/maogai/detail/ch12-examples.md",
        "label": "对毛泽东思想的科学评价"
      },
      "stem": "关于毛泽东思想，1981年《决议》强调（　）。",
      "options": [
        "毛泽东的正确思想属于毛泽东思想，错误思想不属于毛泽东思想",
        "毛泽东所有思想都属于毛泽东思想",
        "毛泽东思想与马克思列宁主义无关",
        "毛泽东思想仅属于毛泽东个人"
      ],
      "answer": 0,
      "hint": "ch12-examples例题2。",
      "explanation": "A正确。ch12-examples：须区分毛泽东个人思想与毛泽东思想。B、C、D均错误。"
    },
    {
      "id": "q014",
      "type": "single_choice",
      "difficulty": "basic",
      "source": "review",
      "sourceChapter": "ch04",
      "points": 2,
      "sourceRef": {
        "path": "content/maogai/detail/4.1.md",
        "label": "经济关系与政治关系决定社会性质"
      },
      "stem": "毛泽东指出，认清一切革命问题的基本依据是（　）。",
      "options": [
        "认清中国社会的性质（国情）",
        "认清外国革命经验",
        "认清古代典籍",
        "认清个人意志"
      ],
      "answer": 0,
      "hint": "4.1.md开篇引语。",
      "explanation": "A正确。4.1.md：认清中国社会性质就是认清国情，是认清一切革命问题的基本依据。"
    },
    {
      "id": "q015",
      "type": "single_choice",
      "difficulty": "basic",
      "source": "review",
      "sourceChapter": "ch16",
      "points": 2,
      "sourceRef": {
        "path": "content/maogai/detail/16.1.md",
        "label": "初步探索的重要意义"
      },
      "stem": "社会主义建设初步探索为开创中国特色社会主义提供了（　）。",
      "options": [
        "宝贵经验、理论准备和物质基础",
        "完整成熟的现成模式",
        "资本主义复辟条件",
        "与社会主义无关的教训"
      ],
      "answer": 0,
      "hint": "16.1.md三方面意义之二。",
      "explanation": "A正确。16.1.md：提供经验、理论准备和物质基础。B“完整成熟现成模式”不符合探索性质；C、D错误。"
    },
    {
      "id": "q016",
      "type": "multiple_choice",
      "difficulty": "basic",
      "source": "current_chapter",
      "sourceChapter": "ch12",
      "points": 2,
      "sourceRef": {
        "path": "content/maogai/detail/12.1.md",
        "label": "确立过程时间线"
      },
      "stem": "实事求是思想路线确立过程中的重要节点包括（　）。",
      "options": [
        "1930年《反对本本主义》",
        "1937年《实践论》《矛盾论》",
        "1938年六届六中全会正式提出概念",
        "1941年《改造我们的学习》系统阐释",
        "1945年七大正式确立"
      ],
      "answer": [
        0,
        1,
        2,
        3,
        4
      ],
      "hint": "时间线表格五个节点。",
      "explanation": "ABCDE全部正确。12.1.md确立过程时间线完整涵盖。"
    },
    {
      "id": "q017",
      "type": "multiple_choice",
      "difficulty": "medium",
      "source": "current_chapter",
      "sourceChapter": "ch12",
      "points": 2,
      "sourceRef": {
        "path": "content/maogai/detail/12.1.md",
        "label": "坚持实事求是的三个层面"
      },
      "stem": "坚持实事求是需要从哪些层面把握？（　）",
      "options": [
        "把握事物内在规律性，按客观规律办事",
        "正确认识和把握国情",
        "在实践基础上推进理论创新",
        "固守教条拒绝任何创新",
        "脱离实际从主观愿望出发"
      ],
      "answer": [
        0,
        1,
        2
      ],
      "hint": "三个层面定义框。",
      "explanation": "ABC正确。12.1.md三个层面。D、E与实事求是相反。"
    },
    {
      "id": "q018",
      "type": "multiple_choice",
      "difficulty": "basic",
      "source": "current_chapter",
      "sourceChapter": "ch12",
      "points": 2,
      "sourceRef": {
        "path": "content/maogai/detail/12.2.md",
        "label": "群众路线的双重属性"
      },
      "stem": "关于群众路线，正确的有（　）。",
      "options": [
        "既是价值立场，也是工作方法",
        "价值立场是一切为了群众、一切依靠群众",
        "工作方法是从群众中来、到群众中去",
        "只要口号响亮不必深入群众",
        "与唯物史观关于人民群众是历史创造者的原理相联系"
      ],
      "answer": [
        0,
        1,
        2,
        4
      ],
      "hint": "12.2.md双重属性及习近平论述。",
      "explanation": "ABCE正确。12.2.md：双重属性及理论根基。D与“到群众中去”矛盾。"
    },
    {
      "id": "q019",
      "type": "multiple_choice",
      "difficulty": "medium",
      "source": "current_chapter",
      "sourceChapter": "ch12",
      "points": 2,
      "sourceRef": {
        "path": "content/maogai/detail/12.3.md",
        "label": "外交三大方针"
      },
      "stem": "新中国成立初期外交三大方针包括（　）。",
      "options": [
        "另起炉灶",
        "打扫干净屋子再请客",
        "一边倒",
        "和平共处五项原则",
        "不结盟政策"
      ],
      "answer": [
        0,
        1,
        2
      ],
      "hint": "三大方针是建国初期，不结盟是改革开放后。",
      "explanation": "ABC正确。12.3.md建国初期三大方针。D是1950s提出但非“三大方针”；E是改革开放后。"
    },
    {
      "id": "q020",
      "type": "multiple_choice",
      "difficulty": "medium",
      "source": "current_chapter",
      "sourceChapter": "ch12",
      "points": 2,
      "sourceRef": {
        "path": "content/maogai/detail/12.2.md",
        "label": "新时代群众路线的实践要求"
      },
      "stem": "新时代坚持群众路线的实践要求包括（　）。",
      "options": [
        "以人民对美好生活的向往为奋斗目标",
        "坚持以人民为中心的发展思想",
        "发展全过程人民民主",
        "让发展成果由人民共享",
        "忽视群众主体地位"
      ],
      "answer": [
        0,
        1,
        2,
        3
      ],
      "hint": "12.2.md第四节。",
      "explanation": "ABCD正确。12.2.md新时代四条要求。E与群众路线根本对立。"
    },
    {
      "id": "q021",
      "type": "multiple_choice",
      "difficulty": "basic",
      "source": "review",
      "sourceChapter": "ch03",
      "points": 2,
      "sourceRef": {
        "path": "content/maogai/detail/ch12-examples.md",
        "label": "对毛泽东思想的科学评价"
      },
      "stem": "《决议》和党章对毛泽东思想的科学界定包括（　）。",
      "options": [
        "马克思主义在中国的运用和发展",
        "被实践证明了的关于中国革命和建设的正确的理论原则和经验总结",
        "中国共产党集体智慧的结晶",
        "毛泽东个人所有言论的汇总",
        "一成不变的教条"
      ],
      "answer": [
        0,
        1,
        2
      ],
      "hint": "ch12-examples例题2 ABC三项。",
      "explanation": "ABC正确。ch12-examples/3.2.md。D、E错误。"
    },
    {
      "id": "q022",
      "type": "multiple_choice",
      "difficulty": "medium",
      "source": "review",
      "sourceChapter": "ch07",
      "points": 2,
      "sourceRef": {
        "path": "content/maogai/detail/7.3.md",
        "label": "三大优良作风"
      },
      "stem": "党的三大优良作风包括（　）。",
      "options": [
        "理论联系实际",
        "密切联系群众",
        "批评与自我批评",
        "实事求是、群众路线、独立自主",
        "武装斗争、统一战线、党的建设"
      ],
      "answer": [
        0,
        1,
        2
      ],
      "hint": "作风与活的灵魂、法宝区分。",
      "explanation": "ABC正确。7.3.md三大优良作风。D是活的灵魂；E是三大法宝。"
    },
    {
      "id": "q023",
      "type": "multiple_choice",
      "difficulty": "medium",
      "source": "review",
      "sourceChapter": "ch12",
      "points": 2,
      "sourceRef": {
        "path": "content/maogai/detail/12.1.md",
        "label": "实事求是的拨乱反正功能"
      },
      "stem": "1976年后实事求是思想路线在拨乱反正中发挥的作用包括（　）。",
      "options": [
        "反对“两个凡是”，纠正“左”的错误",
        "反对全盘否定毛泽东和毛泽东思想",
        "推动真理标准问题讨论",
        "要求区分毛泽东正确思想与错误思想",
        "坚持凡是毛主席决策都不可更改"
      ],
      "answer": [
        0,
        1,
        2,
        3
      ],
      "hint": "既反僵化又反极端。",
      "explanation": "ABCD正确。12.1.md拨乱反正功能。E是“两个凡是”错误观点。"
    },
    {
      "id": "q024",
      "type": "multiple_choice",
      "difficulty": "hard",
      "source": "review",
      "sourceChapter": "ch12",
      "points": 2,
      "sourceRef": {
        "path": "content/maogai/detail/12.3.md",
        "label": "中苏关系四十年演变"
      },
      "stem": "中苏关系演变各阶段与独立自主原则的体现，配对正确的有（　）。",
      "options": [
        "结盟时期——签订友好同盟互助条约，谈判收回东北主权",
        "争吵时期——长波电台之争，半个手指头都不行",
        "争斗时期——珍宝岛冲突，坚持不屈服压力",
        "谈判时期——结束过去开辟未来，在平等基础上正常化",
        "全程完全平等无任何曲折"
      ],
      "answer": [
        0,
        1,
        2,
        3
      ],
      "hint": "12.3.md四阶段表格。",
      "explanation": "ABCD正确。12.3.md四阶段及独立自主体现。E与“不平等”“屈辱”总结矛盾。"
    },
    {
      "id": "q025",
      "type": "multiple_choice",
      "difficulty": "basic",
      "source": "review",
      "sourceChapter": "ch03",
      "points": 2,
      "sourceRef": {
        "path": "content/maogai/detail/3.2.md",
        "label": "马克思主义中国化时代化的内涵"
      },
      "stem": "“两个结合”是指（　）。",
      "options": [
        "坚持马克思主义同中国具体实际相结合",
        "坚持马克思主义同中国优秀传统文化相结合",
        "坚持马克思主义同西方价值观完全融合",
        "坚持马克思主义同本国实际相结合",
        "坚持马克思主义同传统文化相结合（准确表述为中国优秀传统文化）"
      ],
      "answer": [
        0,
        1
      ],
      "hint": "3.2.md两个结合。",
      "explanation": "AB正确。3.2.md：与中国实际相结合、与优秀传统文化相结合。C“西方价值观完全融合”错误；D、E表述不精确（应为“中国”具体实际和“中国优秀”传统文化），但D若理解为同中国实际则与A重复，故不选DE。"
    },
    {
      "id": "q026",
      "type": "essay",
      "difficulty": "basic",
      "label": "简答题",
      "source": "current_chapter",
      "sourceChapter": "ch12",
      "points": 10,
      "total_points": 10,
      "sourceRef": {
        "path": "content/maogai/detail/12.1.md",
        "label": "实事求是的内涵"
      },
      "stem": "简述实事求是思想路线的内涵及确立过程的主要节点。",
      "answer": "内涵：一切从实际出发，理论联系实际，在实践中检验真理和发展真理；毛泽东阐释“实事”是客观事物，“是”是客观规律，“求”是研究。确立过程：1930年《反对本本主义》“没有调查就没有发言权”；1937年《实践论》《矛盾论》奠定哲学基础；1938年六届六中全会正式提出概念；1941年《改造我们的学习》系统阐释；1945年七大正式确立为党的思想路线。",
      "hint": "内涵+五个时间节点。",
      "explanation": "12.1.md核心内容。",
      "scoring_criteria": [
        "内涵完整（4分）",
        "五个节点各1.2分（6分）"
      ]
    },
    {
      "id": "q027",
      "type": "essay",
      "difficulty": "medium",
      "label": "简答题",
      "source": "review",
      "sourceChapter": "ch07",
      "points": 10,
      "total_points": 10,
      "sourceRef": {
        "path": "content/maogai/detail/7.3.md",
        "label": "三大优良作风"
      },
      "stem": "简述毛泽东思想“三大法宝”与“活的灵魂”的区别与联系。",
      "answer": "三大法宝（7.1/7.3）：统一战线、武装斗争、党的建设——是新民主主义革命战胜敌人的两个基本武器（统一战线、武装斗争）和掌握武器的战士（党的组织）。活的灵魂（12.1/3.2）：实事求是、群众路线、独立自主——是贯穿毛泽东思想各组成部分的立场、观点和方法。区别：法宝是革命实践中三个具体武器及其载体；灵魂是更高层面的方法论原则。联系：坚持活的灵魂才能正确运用三大法宝——实事求是指导道路选择，群众路线是统一战线的根本工作路线，独立自主是统一战线中保持领导权的原则（如抗日统一战线）。",
      "hint": "概念+区别+联系举例。",
      "explanation": "综合3.2.md、7.1.md、12.1.md。",
      "scoring_criteria": [
        "三大法宝内涵（3分）",
        "活的灵魂内涵（3分）",
        "区别（2分）",
        "联系（2分）"
      ]
    },
    {
      "id": "q028",
      "type": "essay",
      "difficulty": "hard",
      "label": "论述题",
      "source": "current_chapter",
      "sourceChapter": "ch12",
      "points": 15,
      "total_points": 15,
      "sourceRef": {
        "path": "content/maogai/detail/12.2.md",
        "label": "群众路线的内涵"
      },
      "stem": "论述群众路线的内涵、理论根基及在新时代的实践要求。",
      "answer": "内涵：一切为了群众，一切依靠群众，从群众中来，到群众中去，把党的正确主张变为群众的自觉行动；包含价值立场（为了谁、依靠谁）和工作方法（怎么做）两个层面。理论根基：体现唯物史观关于人民群众是历史创造者的基本原理（习近平指出只有坚持这一原理才能把握历史规律）。坚持层面：①认识前提——人民是历史创造者；②核心要求——全心全意为人民服务；③关系保障——建立血肉联系。新时代要求：以人民对美好生活的向往为奋斗目标；坚持以人民为中心的发展思想；发展全过程人民民主；让改革发展成果更多更公平惠及全体人民，增强获得感幸福感安全感。",
      "hint": "内涵双层+理论+三层面+新时代四要求。",
      "explanation": "12.2.md全文结构。",
      "scoring_criteria": [
        "内涵双层（4分）",
        "理论根基（3分）",
        "坚持三层面（4分）",
        "新时代要求（4分）"
      ]
    },
    {
      "id": "q029",
      "type": "essay",
      "difficulty": "hard",
      "label": "材料分析题",
      "source": "review",
      "sourceChapter": "ch12",
      "points": 15,
      "total_points": 15,
      "sourceRef": {
        "path": "content/maogai/detail/12.3.md",
        "label": "从毛泽东到邓小平的主权立场"
      },
      "stem": "阅读材料，回答问题。\n\n材料一：毛泽东1958年说：“要讲政治条件，连半个手指头都不行。”\n材料二：邓小平1982年对撒切尔夫人说：“只要涉及到国家主权问题，一丝一毫都不能让步。”\n材料三：党的二十大报告：“中国的问题必须从中国基本国情出发，由中国人自己来解答。”\n\n（1）三则材料共同体现了毛泽东思想哪一活的灵魂？其核心内涵是什么？（6分）\n（2）结合中苏关系四十年演变，说明这一原则如何推动中国探索自己的发展道路？（9分）",
      "answer": "（1）体现独立自主。内涵：坚持独立思考走自己的路，维护民族独立捍卫国家主权，既依靠自身力量进行革命和建设，也积极争取外援、学习外国有益事物；独立自主不是闭关自守，而是保持主体性和主动性。（2）中苏关系：结盟时期在援助中争取收回东北主权；争吵时期长波电台和共同舰队之争坚决维护主权；争斗时期在意识形态压力和边境冲突中不屈服；1989年邓小平总结四十年关系实质是不平等，以“结束过去开辟未来”实现正常化。这一过程推动中国从苏联模式剥离，《论十大关系》开始探索中国道路，最终形成中国特色社会主义道路。二十大报告总结：百年奋斗成功道路是党领导人民独立自主探索开辟的，印证独立自主是道路选择原则。",
      "hint": "独立自主+中苏四阶段+道路探索。",
      "explanation": "12.3.md全文及与16.2.md联系。",
      "scoring_criteria": [
        "识别独立自主及内涵（6分）",
        "中苏关系与道路探索（9分）"
      ]
    }
  ],
  "summary": {
    "totalQuestions": 29,
    "byType": {
      "single_choice": 15,
      "multiple_choice": 10,
      "essay": 4
    },
    "bySource": {
      "current_chapter": 15,
      "review": 14
    },
    "byDifficulty": {
      "basic": 20,
      "medium": 6,
      "hard": 3
    }
  }
}