{
  "subjectId": "maogai",
  "chapterId": "rec-10",
  "generatedAt": "2026-07-01",
  "examConfig": {
    "source": "docs/refer/考试题型分布.md",
    "totalPoints": 100,
    "timeLimit": 50
  },
  "questions": [
    {
      "id": "q001",
      "type": "single_choice",
      "difficulty": "basic",
      "source": "current_chapter",
      "sourceChapter": "rec-10",
      "points": 2,
      "stem": "党的十三大明确提出中国处于社会主义初级阶段，其科学含义包含两层，正确的一组是（　）。",
      "options": [
        "从性质看已是社会主义国家，从发展程度看仍处于不发达阶段",
        "从性质看仍是新民主主义社会，从发展程度看已进入发达阶段",
        "从生产力看已经高度发达，从生产关系看尚未完成社会主义改造",
        "从经济看已建成市场经济，从政治看尚处于过渡时期"
      ],
      "answer": 0,
      "hint": "两层含义一层讲“性质不能丢”，一层讲“不能超越阶段”。",
      "explanation": "A正确。14.1.md指出社会主义初级阶段含两层且缺一不可：①从性质上看中国已是社会主义国家，由社会主义改造完成后建立的基本制度决定，决不能动摇；②从发展程度上看仍处于初级即不发达阶段。B错误，社会主义改造完成后已不是新民主主义社会，且中国并未进入发达阶段；C错误，中国生产力水平较低、并非高度发达，且社会主义改造已于1956年完成；D错误，初级阶段是长期历史阶段而非“过渡时期”，市场经济体制也非1987年已建成。",
      "sourceRef": {
        "path": "content/maogai/detail/14.1.md",
        "label": "14.1 社会主义初级阶段理论 · 一、社会主义初级阶段的科学含义"
      }
    },
    {
      "id": "q002",
      "type": "single_choice",
      "difficulty": "basic",
      "source": "current_chapter",
      "sourceChapter": "rec-10",
      "points": 2,
      "stem": "正式明确提出“中国处于社会主义初级阶段”这一重大判断的会议是（　）。",
      "options": [
        "1978年十一届三中全会",
        "1987年党的十三大",
        "1992年党的十四大",
        "1997年党的十五大"
      ],
      "answer": 1,
      "hint": "同一次大会还确立了初级阶段基本路线和“三步走”战略。",
      "explanation": "B正确。14.1.md：1987年党的十三大报告明确指出中国处于社会主义初级阶段，并在此基础上确立了基本路线、提出“三步走”战略。A十一届三中全会实现工作重心转移、确立改革开放方针，但未提出初级阶段判断；C十四大的核心贡献是确立社会主义市场经济体制改革目标；D十五大是把初级阶段特征概括为“九大特征”并阐述基本纲领，是深化而非首次提出。",
      "sourceRef": {
        "path": "content/maogai/detail/14.1.md",
        "label": "14.1 社会主义初级阶段理论 · 三、初级阶段的基本特征"
      }
    },
    {
      "id": "q003",
      "type": "single_choice",
      "difficulty": "medium",
      "source": "current_chapter",
      "sourceChapter": "rec-10",
      "points": 2,
      "stem": "社会主义初级阶段基本路线“一个中心、两个基本点”中，被称为“立国之本”的是（　）。",
      "options": [
        "以经济建设为中心",
        "坚持四项基本原则",
        "坚持改革开放",
        "自力更生、艰苦创业"
      ],
      "answer": 1,
      "hint": "注意区分“立国之本”与“强国之路”分别指向哪一个基本点。",
      "explanation": "B正确。14.1.md：四项基本原则是“立国之本”，规定改革的社会主义方向；坚持改革开放是“强国之路”。C改革开放是“强国之路”而非“立国之本”，是常见的偷换项；A以经济建设为中心是“一个中心”，是根本任务的着力点，不属于“两个基本点”，更不叫“立国之本”；D自力更生、艰苦创业是基本路线的根本立足点，也不是此处所问的称谓。",
      "sourceRef": {
        "path": "content/maogai/detail/14.1.md",
        "label": "14.1 社会主义初级阶段理论 · 五、基本路线的完整表述"
      }
    },
    {
      "id": "q004",
      "type": "single_choice",
      "difficulty": "basic",
      "source": "current_chapter",
      "sourceChapter": "rec-10",
      "points": 2,
      "stem": "1992年邓小平在南方讲话中对社会主义本质作出的完整表述是（　）。",
      "options": [
        "公有制为主体，按劳分配为主体，共同富裕",
        "解放生产力，发展生产力，消灭剥削，消除两极分化，最终达到共同富裕",
        "以经济建设为中心，坚持四项基本原则，坚持改革开放",
        "解放思想，实事求是，与时俱进，求真务实"
      ],
      "answer": 1,
      "hint": "本质表述有“两个层面、五句话”，落脚点是共同富裕。",
      "explanation": "B正确。14.1.md：1992年南方讲话完整表述社会主义本质为“解放生产力，发展生产力，消灭剥削，消除两极分化，最终达到共同富裕”，含生产力与生产关系两个层面。A是社会主义初级阶段的基本经济、分配制度特征，不是“本质”的规范表述；C是党的基本路线内容，回答的是“怎么建设”而非“什么是社会主义”；D是党的思想路线／邓小平理论精髓的表述，属于方法论层面，不是社会主义本质。",
      "sourceRef": {
        "path": "content/maogai/detail/14.1.md",
        "label": "14.1 社会主义初级阶段理论 · 八、社会主义本质论的提出"
      }
    },
    {
      "id": "q005",
      "type": "single_choice",
      "difficulty": "medium",
      "source": "current_chapter",
      "sourceChapter": "rec-10",
      "points": 2,
      "stem": "邓小平提出的判断改革开放和各项工作是非得失的根本标准是“三个有利于”，下列不属于其内容的是（　）。",
      "options": [
        "是否有利于发展社会主义社会的生产力",
        "是否有利于增强社会主义国家的综合国力",
        "是否有利于提高人民的生活水平",
        "是否有利于提高社会的公有化程度"
      ],
      "answer": 3,
      "hint": "“三个有利于”落脚在生产力、综合国力、人民生活，而非所有制形式本身。",
      "explanation": "D正确（即D不属于）。14.1.md：三个有利于指是否有利于发展生产力、增强综合国力、提高人民生活水平。A、B、C三项均为其正确内容。D“提高公有化程度”恰恰是被批判的对象——14.1.md明确指出单纯提高公有化程度并不等于能推动生产力发展，把公有化程度当标准正是“姓社姓资”僵化思维，故不属于“三个有利于”。",
      "sourceRef": {
        "path": "content/maogai/detail/14.1.md",
        "label": "14.1 社会主义初级阶段理论 · 十、社会主义本质论的实践意义 · 三个有利于"
      }
    },
    {
      "id": "q006",
      "type": "single_choice",
      "difficulty": "basic",
      "source": "current_chapter",
      "sourceChapter": "rec-10",
      "points": 2,
      "stem": "邓小平理论的精髓，同时也是党的思想路线，是（　）。",
      "options": [
        "独立自主、自力更生",
        "解放思想、实事求是",
        "和平与发展",
        "一个中心、两个基本点"
      ],
      "answer": 1,
      "hint": "1978年那篇闭幕讲话的标题就点明了它。",
      "explanation": "B正确。14.1.md：解放思想、实事求是是邓小平理论的精髓，也是党的思想路线，1978年邓小平《解放思想，实事求是，团结一致向前看》重新确立并发展了这一路线。A独立自主、自力更生是毛泽东思想活的灵魂之一及立足点，非邓小平理论精髓；C和平与发展是邓小平对时代主题的判断，属国际战略内容；D是社会主义初级阶段基本路线的核心内容，属路线而非“精髓/思想路线”。",
      "sourceRef": {
        "path": "content/maogai/detail/14.1.md",
        "label": "14.1 社会主义初级阶段理论 · 十一、邓小平理论的精髓"
      }
    },
    {
      "id": "q007",
      "type": "single_choice",
      "difficulty": "medium",
      "source": "current_chapter",
      "sourceChapter": "rec-10",
      "points": 2,
      "stem": "实事求是作为党的思想路线最早确立于1945年党的七大；在改革开放前夕重新确立这一思想路线、并增加“解放思想”内容的标志是（　）。",
      "options": [
        "1978年邓小平《解放思想，实事求是，团结一致向前看》的讲话",
        "1981年《关于建国以来党的若干历史问题的决议》",
        "1978年《实践是检验真理的唯一标准》一文的发表",
        "1992年邓小平南方讲话"
      ],
      "answer": 0,
      "hint": "注意题目问的是“重新确立思想路线并增加解放思想”的标志，不是真理标准讨论的开端。",
      "explanation": "A正确。14.1.md：1978年12月中央工作会议闭幕式上，邓小平作《解放思想，实事求是，团结一致向前看》讲话，重新确立实事求是思想路线并增加了“解放思想”内容。B《历史决议》是拨乱反正、系统总结历史问题的标志，非“重新确立思想路线”本身；C真理标准讨论为思想解放作了舆论准备，但“重新确立思想路线”的标志是邓小平的讲话；D南方讲话解决的是计划与市场关系、社会主义本质等问题，时间也晚于重新确立思想路线。",
      "sourceRef": {
        "path": "content/maogai/detail/14.1.md",
        "label": "14.1 社会主义初级阶段理论 · 十一、邓小平理论的精髓 · 解放思想与实事求是"
      }
    },
    {
      "id": "q008",
      "type": "single_choice",
      "difficulty": "medium",
      "source": "current_chapter",
      "sourceChapter": "rec-10",
      "points": 2,
      "stem": "1987年党的十三大提出的“三步走”发展战略中，第一步（1981—1990年）要实现的目标是（　）。",
      "options": [
        "达到小康水平",
        "基本解决温饱问题",
        "达到中等发达国家水平",
        "基本实现社会主义现代化"
      ],
      "answer": 1,
      "hint": "第一步管“吃饱饭”，第二步管“小康”，第三步管“中等发达”。",
      "explanation": "B正确。14.1.md“三步走”表：第一步（1981—1990）国民生产总值比1980年翻一番，基本解决温饱问题。A“小康水平”是第二步（1991—2000）的目标；C“中等发达国家水平、基本实现现代化”是第三步（21世纪中叶）的目标；D基本实现社会主义现代化同属第三步。三个选项都是真实目标，但对应步骤被错位，属典型时序混淆干扰。",
      "sourceRef": {
        "path": "content/maogai/detail/14.1.md",
        "label": "14.1 社会主义初级阶段理论 · 六、根本任务与“三步走”战略"
      }
    },
    {
      "id": "q009",
      "type": "single_choice",
      "difficulty": "basic",
      "source": "current_chapter",
      "sourceChapter": "rec-10",
      "points": 2,
      "stem": "在马克思恩格斯“科学技术是生产力”的基础上，进一步提出“科学技术是第一生产力”论断的是（　）。",
      "options": [
        "毛泽东",
        "邓小平",
        "江泽民",
        "马克思"
      ],
      "answer": 1,
      "hint": "这一论断出现在20世纪80年代，与改革开放和“三步走”同期。",
      "explanation": "B正确。14.1.md：邓小平在1980年代提出“科学技术是第一生产力”，突出科技在生产力发展中的核心驱动地位。A毛泽东未作此论断；C江泽民提出的是“三个代表”重要思想，其中发展先进生产力是内容之一，但“第一生产力”论断的提出者是邓小平；D马克思恩格斯只讲“科学技术是生产力”，“第一”是邓小平的发展。",
      "sourceRef": {
        "path": "content/maogai/detail/14.1.md",
        "label": "14.1 社会主义初级阶段理论 · 六、根本任务 · 科学技术是第一生产力"
      }
    },
    {
      "id": "q010",
      "type": "single_choice",
      "difficulty": "medium",
      "source": "current_chapter",
      "sourceChapter": "rec-10",
      "points": 2,
      "stem": "邓小平称“改革是中国的第二次革命”，对改革性质最准确的理解是（　）。",
      "options": [
        "改革要从根本上改变社会主义基本制度",
        "改革是社会主义制度的自我完善和发展",
        "改革是要用武装斗争推翻旧政权",
        "改革就是全面照搬西方资本主义市场制度"
      ],
      "answer": 1,
      "hint": "“革命”指变革的广度和深度，但方向不是改掉社会主义。",
      "explanation": "B正确。14.2.md：改革称“第二次革命”是就其引起社会变革的广度和深度而言，其性质是社会主义制度的自我完善和发展，对象是束缚生产力的具体体制，而非社会主义基本制度。A错误，改革恰恰不改变社会主义基本制度；C错误，改革是和平的、渐进的，不涉及流血牺牲，不同于新民主主义革命的武装斗争；D错误，改革坚持社会主义方向，反对资产阶级自由化，绝非照搬西方制度。",
      "sourceRef": {
        "path": "content/maogai/detail/14.2.md",
        "label": "14.2 改革开放理论 · 一、改革是第二次革命 · 二、改革的性质"
      }
    },
    {
      "id": "q011",
      "type": "single_choice",
      "difficulty": "hard",
      "source": "current_chapter",
      "sourceChapter": "rec-10",
      "points": 2,
      "stem": "正式确立“我国经济体制改革的目标是建立社会主义市场经济体制”的会议是（　）。",
      "options": [
        "1987年党的十三大",
        "1992年邓小平南方讲话",
        "1992年10月党的十四大",
        "1993年十四届三中全会"
      ],
      "answer": 2,
      "hint": "南方讲话是思想先导，把“目标”写进报告的是随后的党代会。",
      "explanation": "C正确。14.2.md：1992年南方讲话后，全党学习其精神，成果就是1992年10月党的十四大报告，正式提出“经济体制改革的目标是建立社会主义市场经济体制”。B南方讲话提出“计划和市场都是经济手段”，是重大思想突破和先导，但把改革“目标”正式确立下来的是十四大；A十三大确立的是初级阶段基本路线；D十四届三中全会是对十四大目标作出具体制度部署（建立现代企业制度等），是细化而非首次确立。此题干扰项均为真实相关节点，需精确区分“思想突破—目标确立—制度部署”。",
      "sourceRef": {
        "path": "content/maogai/detail/14.2.md",
        "label": "14.2 改革开放理论 · 六、社会主义市场经济体制的正式确立"
      }
    },
    {
      "id": "q012",
      "type": "single_choice",
      "difficulty": "basic",
      "source": "current_chapter",
      "sourceChapter": "rec-10",
      "points": 2,
      "stem": "“一国两制”被正式确定为中国的一项基本国策，是在（　）。",
      "options": [
        "1981年叶剑英发表对台九条方针",
        "1982年宪法第三十一条通过",
        "1985年六届全国人大三次会议",
        "1984年《中英联合声明》签订"
      ],
      "answer": 2,
      "hint": "“雏形—宪法依据—确立为基本国策”是三个不同节点，注意问的是最后一个。",
      "explanation": "C正确。14.2.md：1985年六届全国人大三次会议正式把“一国两制”确定为中国的一项基本国策。A1981年叶剑英对台九条是“一国两制”的雏形；B1982年宪法第三十一条为其提供了宪法依据；D1984年《中英联合声明》是“一国两制”在香港问题上的应用成果。三项都是重要相关节点，但确立为“基本国策”的是1985年六届人大三次会议。",
      "sourceRef": {
        "path": "content/maogai/detail/14.2.md",
        "label": "14.2 改革开放理论 · 十二、“一国两制”的正式提出与内涵"
      }
    },
    {
      "id": "q013",
      "type": "single_choice",
      "difficulty": "medium",
      "source": "current_chapter",
      "sourceChapter": "rec-10",
      "points": 2,
      "stem": "按照“一国两制”下的权力划分，香港特别行政区享有的权力是（　）。",
      "options": [
        "外交权",
        "国防权",
        "独立的司法权和财政权",
        "主要官员的最终任命权"
      ],
      "answer": 2,
      "hint": "涉及国家主权的权力归中央，特区自治权是“行政、立法、司法、财政”。",
      "explanation": "C正确。14.2.md香港权力架构：特别行政区享有行政权、立法权、司法权和独立的财政权（财政收入全部用于自身、不上交中央、中央不在港征税）。A外交权、B国防权、D主要官员任命权均属中央人民政府，是国家主权的体现，不属于特区。此题专门针对“财政权归特区、任命权归中央”这一易混点设计。",
      "sourceRef": {
        "path": "content/maogai/detail/14.2.md",
        "label": "14.2 改革开放理论 · 十三、香港特别行政区的权力架构"
      }
    },
    {
      "id": "q014",
      "type": "multiple_choice",
      "difficulty": "basic",
      "source": "current_chapter",
      "sourceChapter": "rec-10",
      "points": 2,
      "stem": "邓小平关于社会主义本质的科学论断包括（　）。",
      "options": [
        "解放生产力，发展生产力",
        "消灭剥削，消除两极分化",
        "最终达到共同富裕",
        "立即消灭一切非公有制经济"
      ],
      "answer": [
        0,
        1,
        2
      ],
      "hint": "本质是“五句话、两层面”，最后落脚共同富裕；注意有一项把手段绝对化了。",
      "explanation": "正确答案ABC。14.1.md：社会主义本质是“解放生产力、发展生产力（生产力层面）+消灭剥削、消除两极分化、最终达到共同富裕（生产关系层面）”。A、B、C分别对应这五句话。D错误且极具迷惑性——社会主义初级阶段坚持公有制为主体，同时允许个体、私营等非公有制经济发展，本质论从未要求“立即消灭一切非公有制经济”，这与初级阶段国情和“三个有利于”标准直接冲突，最易被误选，务必排除。",
      "sourceRef": {
        "path": "content/maogai/detail/14.1.md",
        "label": "14.1 社会主义初级阶段理论 · 八、社会主义本质论的提出"
      }
    },
    {
      "id": "q015",
      "type": "multiple_choice",
      "difficulty": "medium",
      "source": "current_chapter",
      "sourceChapter": "rec-10",
      "points": 2,
      "stem": "社会主义初级阶段基本路线中的“两个基本点”是指（　）。",
      "options": [
        "坚持四项基本原则",
        "坚持改革开放",
        "以经济建设为中心",
        "坚持独立自主、自力更生"
      ],
      "answer": [
        0,
        1
      ],
      "hint": "“一个中心、两个基本点”里，中心与基本点不要混为一类。",
      "explanation": "正确答案AB。14.1.md：“两个基本点”即坚持四项基本原则（立国之本）和坚持改革开放（强国之路），二者相互依存、不可偏废。C“以经济建设为中心”是“一个中心”，是最易误选的干扰项——它是根本任务的着力点，不属于“两个基本点”；D独立自主、自力更生是我们的立足点和优良传统，但不是基本路线所概括的“两个基本点”。多选题在此最常见的失分点就是把“一个中心”错当成基本点漏判或错选。",
      "sourceRef": {
        "path": "content/maogai/detail/14.1.md",
        "label": "14.1 社会主义初级阶段理论 · 五、基本路线的完整表述"
      }
    },
    {
      "id": "q016",
      "type": "multiple_choice",
      "difficulty": "medium",
      "source": "current_chapter",
      "sourceChapter": "rec-10",
      "points": 2,
      "stem": "20世纪80年代的改革进程中，曾引发“姓社姓资”激烈争论的领域有（　）。",
      "options": [
        "家庭联产承包责任制",
        "兴办经济特区",
        "发展商品经济、市场经济",
        "实行家庭联产承包制之外的土地私有化"
      ],
      "answer": [
        0,
        1,
        2
      ],
      "hint": "回忆四大争论领域；有一项是原文从未主张、也与土地公有制相悖的说法。",
      "explanation": "正确答案ABC。14.2.md列出四大引发姓社姓资争论的领域：家庭联产承包责任制、经济特区、商品经济、市场经济（其中市场经济争论最激烈）。A、B、C准确对应。D“土地私有化”错误——家庭联产承包责任制是在坚持土地集体所有制前提下的经营方式变革，中国从未推行“土地私有化”，该项把改革歪曲为私有化，属似是而非的迷惑项，须排除。",
      "sourceRef": {
        "path": "content/maogai/detail/14.2.md",
        "label": "14.2 改革开放理论 · 四、姓“社”姓“资”争论的全过程"
      }
    },
    {
      "id": "q017",
      "type": "multiple_choice",
      "difficulty": "hard",
      "source": "current_chapter",
      "sourceChapter": "rec-10",
      "points": 2,
      "stem": "关于社会主义市场经济的科学内涵，下列表述正确的有（　）。",
      "options": [
        "计划经济和市场经济不是划分社会主义与资本主义的标志",
        "计划和市场都是经济手段",
        "坚持社会主义制度与市场经济结合是其特色所在、优势所在",
        "市场经济必然导致私有化，因而社会主义不能搞市场经济"
      ],
      "answer": [
        0,
        1,
        2
      ],
      "hint": "前三点是南方讲话与十四大确立的要点；有一项恰是被彻底否定的旧观念。",
      "explanation": "正确答案ABC。14.2.md“社会主义市场经济的三个要点”：①计划与市场不是划分社会主义制度的标志；②计划和市场都是经济手段；③坚持社会主义制度与市场经济结合，是其特色所在、优势所在。A、B、C准确对应。D错误——它正是南方讲话所打破的“市场经济=资本主义”的僵化观念；社会主义可以搞市场经济，通过公有制主体地位与共同富裕保证不走向私有化和两极分化，故D必须排除。",
      "sourceRef": {
        "path": "content/maogai/detail/14.2.md",
        "label": "14.2 改革开放理论 · 七、社会主义市场经济的三个要点"
      }
    },
    {
      "id": "q018",
      "type": "multiple_choice",
      "difficulty": "medium",
      "source": "current_chapter",
      "sourceChapter": "rec-10",
      "points": 2,
      "stem": "“一国两制”构想的基本内涵包括（　）。",
      "options": [
        "坚持一个中国是前提和基础",
        "大陆实行社会主义，港澳台保持资本主义，长期并存",
        "特别行政区享有高度自治权",
        "尽最大努力争取和平统一，同时不承诺放弃使用武力"
      ],
      "answer": [
        0,
        1,
        2,
        3
      ],
      "hint": "内涵分“一国—两制—高度自治”和“和平统一—不承诺弃武”两层，四项都要看。",
      "explanation": "正确答案ABCD（全选）。14.2.md“一国两制的内涵”含两层：第一层——“一国”是前提（A）、两制并存（B）、特别行政区高度自治（C）；第二层——尽最大努力争取和平统一，但不承诺放弃使用武力（D）。四项均为原文明确内容。此题易失分处在于漏选D：不少同学只记“一国两制、高度自治”而忽略“不承诺放弃武力”这一针对外部干涉和“台独”的底线，导致漏选，须完整把握两层内涵。",
      "sourceRef": {
        "path": "content/maogai/detail/14.2.md",
        "label": "14.2 改革开放理论 · 十二、“一国两制”的正式提出与内涵"
      }
    },
    {
      "id": "q019",
      "type": "multiple_choice",
      "difficulty": "hard",
      "source": "current_chapter",
      "sourceChapter": "rec-10",
      "points": 2,
      "stem": "在“一国两制”下，属于中央人民政府对香港特别行政区行使的权力有（　）。",
      "options": [
        "外交权",
        "国防权",
        "主要官员任命权",
        "特别行政区的财政收入征收与支配权"
      ],
      "answer": [
        0,
        1,
        2
      ],
      "hint": "涉及国家主权的归中央；有一项属于特区高度自治范围，注意别把它划给中央。",
      "explanation": "正确答案ABC。14.2.md香港权力架构：中央人民政府行使外交权、国防权、主要官员任命权（均属国家主权）。A、B、C正确。D错误——财政权属于特区高度自治权，香港财政收入全部用于自身需要、不上交中央，中央也不在港征税，故“财政收入的征收与支配权”不属于中央。本题与单选q013互为镜像，专门检验“主权性权力归中央、自治性权力（含财政）归特区”的界限，最易误选D。",
      "sourceRef": {
        "path": "content/maogai/detail/14.2.md",
        "label": "14.2 改革开放理论 · 十三、香港特别行政区的权力架构"
      }
    },
    {
      "id": "q020",
      "type": "multiple_choice",
      "difficulty": "medium",
      "source": "current_chapter",
      "sourceChapter": "rec-10",
      "points": 2,
      "stem": "邓小平提出的“两手抓、两手都要硬”，在实践中体现为（　）。",
      "options": [
        "一手抓物质文明，一手抓精神文明",
        "一手抓建设，一手抓法治",
        "一手抓改革开放，一手抓惩治腐败",
        "一手抓经济建设，一手抓阶级斗争"
      ],
      "answer": [
        0,
        1,
        2
      ],
      "hint": "“两手抓”的三组搭配都围绕改革开放的健康方向；有一项是被否定的旧提法。",
      "explanation": "正确答案ABC。14.2.md“两手抓”表：物质文明与精神文明、建设与法治、改革开放与惩治腐败，三组搭配都要求“两手都要硬”，确保改革不偏离社会主义方向。A、B、C正确。D错误——“以阶级斗争为纲”正是十一届三中全会所纠正、被彻底否定的错误路线，与以经济建设为中心相冲突，绝不属于邓小平的“两手抓”，是明显的迷惑项。",
      "sourceRef": {
        "path": "content/maogai/detail/14.2.md",
        "label": "14.2 改革开放理论 · 九、“两手抓”的完整内涵"
      }
    }
  ]
}